LICENSE.txt
MANIFEST.in
README.md
README.rst
setup.py
gcnParser/__init__.py
gcnParser/__version__.py
gcnParser/cl_utils.py
gcnParser/default_settings.yaml
gcnParser/setup.cfg
gcnParser/utKit.py
gcnParser.egg-info/PKG-INFO
gcnParser.egg-info/SOURCES.txt
gcnParser.egg-info/dependency_links.txt
gcnParser.egg-info/not-zip-safe
gcnParser.egg-info/requires.txt
gcnParser.egg-info/top_level.txt
gcnParser/commonutils/__init__.py
gcnParser/commonutils/getpackagepath.py
gcnParser/tests/__init__.py
gcnParser/tests/input/example_settings.yaml