Metadata-Version: 1.1
Name: gcnParser
Version: 0.1
Summary: A python package and command-line tools to Parse GCN Notices and Circulars into a MySQL Database
Home-page: https://github.com/thespacedoctor/gcnParser
Author: David Young
Author-email: davidrobertyoung@gmail.com
License: MIT
Download-URL: https://github.com/thespacedoctor/gcnParser/archive/v0.1.zip
Keywords: gcn, parse, mysql
Platform: UNKNOWN
Classifier: Development Status :: 4 - Beta
Classifier: License :: OSI Approved :: MIT License
Classifier: Programming Language :: Python :: 2.7
Classifier: Topic :: Utilities
